<annotation>
	<folder>02</folder>
	<filename>3429946947_1466310dcd_o.jpg</filename>
	<path>C:\Users\caate\Documents\2nd YEAR MASTER\Computer Vision\02\3429946947_1466310dcd_o.jpg</path>
	<source>
		<database>Unknown</database>
	</source>
	<size>
		<width>1740</width>
		<height>1195</height>
		<depth>3</depth>
	</size>
	<segmented>0</segmented>
	<object>
		<name>Nike</name>
		<pose>Unspecified</pose>
		<truncated>0</truncated>
		<difficult>0</difficult>
		<bndbox>
			<xmin>551</xmin>
			<ymin>607</ymin>
			<xmax>1097</xmax>
			<ymax>826</ymax>
		</bndbox>
	</object>
</annotation>
