<annotation>
	<folder>01 (chia)</folder>
	<filename>3992539088_9c0d2c1eb6_o.jpg</filename>
	<path>C:\Users\diboc\Documents\Università\2° ANNO DSBA\Computer Vision - Grossetti Rubera\00_Lab\01 (chia)\3992539088_9c0d2c1eb6_o.jpg</path>
	<source>
		<database>Unknown</database>
	</source>
	<size>
		<width>3160</width>
		<height>1634</height>
		<depth>3</depth>
	</size>
	<segmented>0</segmented>
	<object>
		<name>nike</name>
		<pose>Unspecified</pose>
		<truncated>0</truncated>
		<difficult>0</difficult>
		<bndbox>
			<xmin>1557</xmin>
			<ymin>1082</ymin>
			<xmax>1893</xmax>
			<ymax>1214</ymax>
		</bndbox>
	</object>
	<object>
		<name>nike</name>
		<pose>Unspecified</pose>
		<truncated>0</truncated>
		<difficult>0</difficult>
		<bndbox>
			<xmin>1989</xmin>
			<ymin>989</ymin>
			<xmax>2036</xmax>
			<ymax>1036</ymax>
		</bndbox>
	</object>
	<object>
		<name>nike</name>
		<pose>Unspecified</pose>
		<truncated>0</truncated>
		<difficult>0</difficult>
		<bndbox>
			<xmin>2455</xmin>
			<ymin>914</ymin>
			<xmax>2523</xmax>
			<ymax>957</ymax>
		</bndbox>
	</object>
	<object>
		<name>nike</name>
		<pose>Unspecified</pose>
		<truncated>0</truncated>
		<difficult>0</difficult>
		<bndbox>
			<xmin>114</xmin>
			<ymin>697</ymin>
			<xmax>308</xmax>
			<ymax>929</ymax>
		</bndbox>
	</object>
	<object>
		<name>nike</name>
		<pose>Unspecified</pose>
		<truncated>0</truncated>
		<difficult>0</difficult>
		<bndbox>
			<xmin>419</xmin>
			<ymin>461</ymin>
			<xmax>742</xmax>
			<ymax>582</ymax>
		</bndbox>
	</object>
	<object>
		<name>nike</name>
		<pose>Unspecified</pose>
		<truncated>0</truncated>
		<difficult>0</difficult>
		<bndbox>
			<xmin>2634</xmin>
			<ymin>927</ymin>
			<xmax>2780</xmax>
			<ymax>1078</ymax>
		</bndbox>
	</object>
</annotation>
