<annotation>
	<folder>Nike</folder>
	<filename>95.ntlondon01_thumb.png</filename>
	<path>C:\Users\kampw\Desktop\Nike\95.ntlondon01_thumb.png</path>
	<source>
		<database>Unknown</database>
	</source>
	<size>
		<width>810</width>
		<height>456</height>
		<depth>3</depth>
	</size>
	<segmented>0</segmented>
	<object>
		<name>Nike</name>
		<pose>Unspecified</pose>
		<truncated>0</truncated>
		<difficult>0</difficult>
		<bndbox>
			<xmin>399</xmin>
			<ymin>327</ymin>
			<xmax>430</xmax>
			<ymax>343</ymax>
		</bndbox>
	</object>
</annotation>
