<annotation verified="yes">
	<folder>adidas</folder>
	<filename>adidas_266.png</filename>
	<path>/Users/BosaniPietro/Desktop/Academics/Bocconi/DSBA/Classes/Semester 3/Deep Learning for Computer Vision/Labelling Task/adidas/adidas_266.png</path>
	<source>
		<database>Unknown</database>
	</source>
	<size>
		<width>628</width>
		<height>280</height>
		<depth>1</depth>
	</size>
	<segmented>0</segmented>
	<object>
		<name>Adidas</name>
		<pose>Unspecified</pose>
		<truncated>0</truncated>
		<difficult>0</difficult>
		<bndbox>
			<xmin>29</xmin>
			<ymin>28</ymin>
			<xmax>325</xmax>
			<ymax>237</ymax>
		</bndbox>
	</object>
	<object>
		<name>Adidas</name>
		<pose>Unspecified</pose>
		<truncated>0</truncated>
		<difficult>0</difficult>
		<bndbox>
			<xmin>370</xmin>
			<ymin>30</ymin>
			<xmax>592</xmax>
			<ymax>236</ymax>
		</bndbox>
	</object>
</annotation>
