<annotation>
	<folder>UA_Andrea</folder>
	<filename>110702395_327231041778210_4121749031949760384_n.jpg</filename>
	<path>C:\Users\acer\Desktop\UA_labael\UA_Andrea\110702395_327231041778210_4121749031949760384_n.jpg</path>
	<source>
		<database>Unknown</database>
	</source>
	<size>
		<width>1080</width>
		<height>1080</height>
		<depth>3</depth>
	</size>
	<segmented>0</segmented>
	<object>
		<name>Under_Armour</name>
		<pose>Unspecified</pose>
		<truncated>0</truncated>
		<difficult>0</difficult>
		<bndbox>
			<xmin>703</xmin>
			<ymin>259</ymin>
			<xmax>770</xmax>
			<ymax>355</ymax>
		</bndbox>
	</object>
	<object>
		<name>Under_Armour</name>
		<pose>Unspecified</pose>
		<truncated>0</truncated>
		<difficult>0</difficult>
		<bndbox>
			<xmin>749</xmin>
			<ymin>842</ymin>
			<xmax>862</xmax>
			<ymax>906</ymax>
		</bndbox>
	</object>
</annotation>
