<annotation>
	<folder>ANNOTATED IMAGES</folder>
	<filename>2016-12-18_01-42-05_UTC.jpg</filename>
	<path>C:\Users\simon\Desktop\Under_Armour_Project\ANNOTATED IMAGES\2016-12-18_01-42-05_UTC.jpg</path>
	<source>
		<database>Unknown</database>
	</source>
	<size>
		<width>720</width>
		<height>720</height>
		<depth>3</depth>
	</size>
	<segmented>0</segmented>
	<object>
		<name>Under_Armour</name>
		<pose>Unspecified</pose>
		<truncated>0</truncated>
		<difficult>0</difficult>
		<bndbox>
			<xmin>333</xmin>
			<ymin>346</ymin>
			<xmax>391</xmax>
			<ymax>375</ymax>
		</bndbox>
	</object>
</annotation>
