<annotation>
	<folder>ua_100</folder>
	<filename>2017-03-03_19-30-06_UTC_3.jpg</filename>
	<path>C:\Users\darry\OneDrive\Desktop\ua_100\2017-03-03_19-30-06_UTC_3.jpg</path>
	<source>
		<database>Unknown</database>
	</source>
	<size>
		<width>710</width>
		<height>710</height>
		<depth>3</depth>
	</size>
	<segmented>0</segmented>
	<object>
		<name>Under_Armour</name>
		<pose>Unspecified</pose>
		<truncated>0</truncated>
		<difficult>0</difficult>
		<bndbox>
			<xmin>252</xmin>
			<ymin>209</ymin>
			<xmax>311</xmax>
			<ymax>259</ymax>
		</bndbox>
	</object>
	<object>
		<name>Under_Armour</name>
		<pose>Unspecified</pose>
		<truncated>0</truncated>
		<difficult>0</difficult>
		<bndbox>
			<xmin>310</xmin>
			<ymin>500</ymin>
			<xmax>352</xmax>
			<ymax>553</ymax>
		</bndbox>
	</object>
</annotation>
