<annotation>
	<folder>201_300</folder>
	<filename>5914379718_cb0e4de77d_o.jpg</filename>
	<path>D:\Bocconi - 2nd year\20600 Deep learning\201_300\201_300\5914379718_cb0e4de77d_o.jpg</path>
	<source>
		<database>Unknown</database>
	</source>
	<size>
		<width>2400</width>
		<height>3000</height>
		<depth>3</depth>
	</size>
	<segmented>0</segmented>
	<object>
		<name>Under_Armour</name>
		<pose>Unspecified</pose>
		<truncated>0</truncated>
		<difficult>0</difficult>
		<bndbox>
			<xmin>540</xmin>
			<ymin>1821</ymin>
			<xmax>603</xmax>
			<ymax>1878</ymax>
		</bndbox>
	</object>
	<object>
		<name>Under_Armour</name>
		<pose>Unspecified</pose>
		<truncated>0</truncated>
		<difficult>0</difficult>
		<bndbox>
			<xmin>1010</xmin>
			<ymin>1028</ymin>
			<xmax>1070</xmax>
			<ymax>1081</ymax>
		</bndbox>
	</object>
	<object>
		<name>Under_Armour</name>
		<pose>Unspecified</pose>
		<truncated>0</truncated>
		<difficult>0</difficult>
		<bndbox>
			<xmin>1641</xmin>
			<ymin>889</ymin>
			<xmax>1706</xmax>
			<ymax>939</ymax>
		</bndbox>
	</object>
</annotation>
