<annotation>
	<folder>underarmour</folder>
	<filename>image_309.jpg</filename>
	<path>D:\Desktop\underarmour\image_309.jpg</path>
	<source>
		<database>Unknown</database>
	</source>
	<size>
		<width>187</width>
		<height>270</height>
		<depth>3</depth>
	</size>
	<segmented>0</segmented>
	<object>
		<name>Under_Armour</name>
		<pose>Unspecified</pose>
		<truncated>0</truncated>
		<difficult>0</difficult>
		<bndbox>
			<xmin>121</xmin>
			<ymin>124</ymin>
			<xmax>140</xmax>
			<ymax>134</ymax>
		</bndbox>
	</object>
</annotation>
